odoo/addons/account_statement_import_base/README.rst
odoo/addons/account_statement_import_base/__init__.py
odoo/addons/account_statement_import_base/__manifest__.py
odoo/addons/account_statement_import_base/i18n/account_statement_import_base.pot
odoo/addons/account_statement_import_base/i18n/ca.po
odoo/addons/account_statement_import_base/i18n/es.po
odoo/addons/account_statement_import_base/i18n/fr.po
odoo/addons/account_statement_import_base/i18n/hr.po
odoo/addons/account_statement_import_base/i18n/it.po
odoo/addons/account_statement_import_base/i18n/pt_BR.po
odoo/addons/account_statement_import_base/i18n/zh_CN.po
odoo/addons/account_statement_import_base/models/__init__.py
odoo/addons/account_statement_import_base/models/account_bank_statement_line.py
odoo/addons/account_statement_import_base/models/account_journal.py
odoo/addons/account_statement_import_base/readme/CONTRIBUTORS.md
odoo/addons/account_statement_import_base/readme/DESCRIPTION.md
odoo/addons/account_statement_import_base/static/description/icon.png
odoo/addons/account_statement_import_base/static/description/index.html
odoo/addons/account_statement_import_base/views/account_bank_statement_line.xml
odoo_addon_account_statement_import_base-19.0.1.0.0.2.dist-info/METADATA
odoo_addon_account_statement_import_base-19.0.1.0.0.2.dist-info/WHEEL
odoo_addon_account_statement_import_base-19.0.1.0.0.2.dist-info/top_level.txt
odoo_addon_account_statement_import_base-19.0.1.0.0.2.dist-info/RECORD
